D1scordX/D1scordX.py
D1scordX/__init__.py
D1scordX-0.0.9.dist-info/LICENSE
D1scordX-0.0.9.dist-info/METADATA
D1scordX-0.0.9.dist-info/WHEEL
D1scordX-0.0.9.dist-info/top_level.txt
D1scordX-0.0.9.dist-info/RECORD
