Metadata-Version: 2.1
Name: D1scordX
Version: 0.0.9
Summary: D1scordX AIO Module
Home-page: UNKNOWN
Author: хıи"RCΛ#7777
Author-email: xingodcontact@gmail.com
License: MIT License
Platform: UNKNOWN
Classifier: Environment :: Web Environment
Classifier: Intended Audience :: Developers
Classifier: License :: OSI Approved :: MIT License
Classifier: Operating System :: OS Independent
Classifier: Programming Language :: Python
Classifier: Programming Language :: Python :: 3.6
Classifier: Programming Language :: Python :: 3.7
Requires-Dist: requests
Requires-Dist: aiohttp
Requires-Dist: discord
Requires-Dist: unidecode
Requires-Dist: numpy
Requires-Dist: colorama
Requires-Dist: discord-webhooks
